nanopyd/__init__.py
nanopyd/nanoid.py
nanopyd-0.1.1.dist-info/LICENSE
nanopyd-0.1.1.dist-info/WHEEL
nanopyd-0.1.1.dist-info/METADATA
nanopyd-0.1.1.dist-info/RECORD
